flamingo/__init__.py
flamingo/__main__.py
flamingo/cli/__init__.py
flamingo/cli/run.py
flamingo/cli/schema.py
flamingo/integrations/__init__.py
flamingo/integrations/huggingface/__init__.py
flamingo/integrations/huggingface/adapter_config.py
flamingo/integrations/huggingface/dataset_config.py
flamingo/integrations/huggingface/loading_utils.py
flamingo/integrations/huggingface/model_config.py
flamingo/integrations/huggingface/quantization_config.py
flamingo/integrations/huggingface/repo_config.py
flamingo/integrations/huggingface/tokenizer_config.py
flamingo/integrations/huggingface/trainer_config.py
flamingo/integrations/wandb/__init__.py
flamingo/integrations/wandb/artifact_config.py
flamingo/integrations/wandb/artifact_utils.py
flamingo/integrations/wandb/run_config.py
flamingo/integrations/wandb/run_utils.py
flamingo/jobs/__init__.py
flamingo/jobs/finetuning/__init__.py
flamingo/jobs/finetuning/config.py
flamingo/jobs/finetuning/entrypoint.py
flamingo/jobs/lm_harness/__init__.py
flamingo/jobs/lm_harness/config.py
flamingo/jobs/lm_harness/entrypoint.py
flamingo/jobs/simple/__init__.py
flamingo/jobs/simple/config.py
flamingo/jobs/simple/entrypoint.py
flamingo/jobs/utils.py
flamingo/types.py
flamingo_ray-0.1.2.dist-info/LICENSE.md
flamingo_ray-0.1.2.dist-info/METADATA
flamingo_ray-0.1.2.dist-info/WHEEL
flamingo_ray-0.1.2.dist-info/entry_points.txt
flamingo_ray-0.1.2.dist-info/RECORD
