Metadata-Version: 2.1
Name: flamingo-ray
Version: 0.1.2
Summary: Ray-centric job library for training and evaluation.
Home-page: https://github.com/mozilla-ai/flamingo
License: Apache-2.0
Author: Sean Friedowitz
Author-email: sean@mozilla.ai
Requires-Python: >=3.10,<3.11
Classifier: License :: OSI Approved :: Apache Software License
Classifier: Programming Language :: Python :: 3
Classifier: Programming Language :: Python :: 3.10
Requires-Dist: click (==8.1.7)
Requires-Dist: protobuf (==3.20.0)
Requires-Dist: pydantic (==2.6.0)
Requires-Dist: pydantic-yaml (==1.2.0)
Requires-Dist: ray[default] (==2.9.1)
Requires-Dist: scipy (==1.10.1)
Requires-Dist: torch (==2.1.2)
Requires-Dist: urllib3 (>=1.26.18,<2)
Requires-Dist: wandb (==0.16.2)
Project-URL: Repository, https://github.com/mozilla-ai/flamingo
